galileoexperiments/__init__.py
galileoexperiments/api/__init__.py
galileoexperiments/api/model.py
galileoexperiments/api/profiling.py
galileoexperiments/experiment/__init__.py
galileoexperiments/experiment/run.py
galileoexperiments/experiment/profiling/__init__.py
galileoexperiments/experiment/profiling/run.py
galileoexperiments/experiment/scenario/__init__.py
galileoexperiments/experiment/scenario/run.py
galileoexperiments/utils/__init__.py
galileoexperiments/utils/arrivalprofile.py
galileoexperiments/utils/constants.py
galileoexperiments/utils/helpers.py
galileoexperiments/utils/k8s.py
galileoexperiments/utils/rds.py
edgerun_galileo_experiments-0.0.1.dist-info/LICENSE
edgerun_galileo_experiments-0.0.1.dist-info/METADATA
edgerun_galileo_experiments-0.0.1.dist-info/WHEEL
edgerun_galileo_experiments-0.0.1.dist-info/top_level.txt
edgerun_galileo_experiments-0.0.1.dist-info/RECORD
