Metadata-Version: 2.1
Name: edgerun-galileo-experiments
Version: 0.0.1
Summary: Galileo Experiments
Home-page: https://github.com/edgerun/galileo-experiments
Author: Philipp Raith, Thomas Rausch
Author-email: p.raith@dsg.tuwien.ac.at, t.rausch@dsg.tuwien.ac.at
License: UNKNOWN
Platform: UNKNOWN
Classifier: Programming Language :: Python :: 3
Classifier: Operating System :: OS Independent
License-File: LICENSE
Requires-Dist: edgerun-galileo (==0.10.4.dev2)
Requires-Dist: galileo-db (==0.10.4.dev1)
Requires-Dist: redis (~=3.5.3)
Requires-Dist: mysql-connector-python (==8.0.16)
Requires-Dist: kubernetes (==18.20.0)
Requires-Dist: influxdb-client (==1.20.0)
Requires-Dist: python-dotenv
Requires-Dist: etcd3 (==0.12.0)
